kineuron/__init__.py
kineuron/kinetic_model.py
kineuron/neuromuscular.py
kineuron/rate_constant.py
kineuron/solver.py
kineuron/stimulation.py
kineuron/transition.py
kineuron/transition_state.py
kineuron-0.1.3.dist-info/LICENSE
kineuron-0.1.3.dist-info/METADATA
kineuron-0.1.3.dist-info/WHEEL
kineuron-0.1.3.dist-info/top_level.txt
kineuron-0.1.3.dist-info/RECORD
