Metadata-Version: 2.1
Name: kineuron
Version: 0.1.3
Summary: Python implementation of the kinetic model of neuromuscular transmission dynamics.
Home-page: https://github.com/alexini-mv/kinetic-neurotransmission
Author: Alejandro Martínez-Valencia
Author-email: al.martinez.valencia@gmail.com
License: UNKNOWN
Project-URL: Bug Tracker, https://github.com/alexini-mv/kinetic-neurotransmission/issues
Project-URL: Source, https://github.com/alexini-mv/kinetic-neurotransmission
Platform: UNKNOWN
Classifier: Programming Language :: Python :: 3
Classifier: Programming Language :: Python :: 3.6
Classifier: Programming Language :: Python :: 3.7
Classifier: Programming Language :: Python :: 3.8
Classifier: Programming Language :: Python :: 3.9
Classifier: Programming Language :: Python :: 3.10
Classifier: License :: OSI Approved :: GNU General Public License v3 (GPLv3)
Classifier: Operating System :: OS Independent
Classifier: Development Status :: 5 - Production/Stable
Classifier: Intended Audience :: Science/Research
Classifier: Topic :: Scientific/Engineering :: Bio-Informatics
Classifier: Topic :: Scientific/Engineering :: Medical Science Apps.
Requires-Python: >=3.6
License-File: LICENSE
Requires-Dist: graphviz (>=0.19.1)
Requires-Dist: matplotlib (>=3.3.4)
Requires-Dist: numpy (>=1.19.5)
Requires-Dist: pandas (>=1.1.5)
Requires-Dist: tqdm (>=4.62.3)
